epubcheck/.gitignore
epubcheck/__init__.py
epubcheck/__main__.py
epubcheck/CHANGELOG.txt
epubcheck/checker.py
epubcheck/cli.py
epubcheck/compat.py
epubcheck/const.py
epubcheck/COPYING.txt
epubcheck/epubcheck.jar
epubcheck/lib/accessors-smart-2.4.9.jar
epubcheck/lib/asm-9.3.jar
epubcheck/lib/checker-qual-3.12.0.jar
epubcheck/lib/common-image-3.9.4.jar
epubcheck/lib/common-io-3.9.4.jar
epubcheck/lib/common-lang-3.9.4.jar
epubcheck/lib/commons-codec-1.15.jar
epubcheck/lib/commons-compress-1.21.jar
epubcheck/lib/error_prone_annotations-2.11.0.jar
epubcheck/lib/failureaccess-1.0.1.jar
epubcheck/lib/galimatias-0.1.3.jar
epubcheck/lib/guava-31.1-jre.jar
epubcheck/lib/httpclient5-5.1.3.jar
epubcheck/lib/httpcore5-5.1.3.jar
epubcheck/lib/httpcore5-h2-5.1.3.jar
epubcheck/lib/icu4j-72.1.jar
epubcheck/lib/imageio-core-3.9.4.jar
epubcheck/lib/imageio-jpeg-3.9.4.jar
epubcheck/lib/imageio-metadata-3.9.4.jar
epubcheck/lib/isorelax-20030108.jar
epubcheck/lib/j2objc-annotations-1.3.jar
epubcheck/lib/jackson-core-asl-1.9.12.jar
epubcheck/lib/jackson-mapper-asl-1.9.12.jar
epubcheck/lib/jing-20181222.jar
epubcheck/lib/json-path-2.8.0.jar
epubcheck/lib/json-path-assert-2.8.0.jar
epubcheck/lib/json-smart-2.4.10.jar
epubcheck/lib/jsr305-3.0.2.jar
epubcheck/lib/listenablefuture-9999.0-empty-to-avoid-conflict-with-guava.jar
epubcheck/lib/sac-1.3.jar
epubcheck/lib/Saxon-HE-11.4.jar
epubcheck/lib/slf4j-api-1.7.36.jar
epubcheck/lib/slf4j-nop-1.7.36.jar
epubcheck/lib/xercesImpl-2.9.1.jar
epubcheck/lib/xml-apis-1.4.01.jar
epubcheck/lib/xmlresolver-4.4.3-data.jar
epubcheck/lib/xmlresolver-4.4.3.jar
epubcheck/LICENSE.txt
epubcheck/licenses/Apache-2.0.txt
epubcheck/licenses/BSD-3-Clause.txt
epubcheck/licenses/MIT.txt
epubcheck/licenses/MPL-2.0.txt
epubcheck/licenses/W3C.txt
epubcheck/models.py
epubcheck/README.txt
epubcheck/samples/__init__.py
epubcheck/samples/childrens-literature.epub
epubcheck/samples/help.txt
epubcheck/samples/invalid.epub
epubcheck/samples/messages.csv
epubcheck-5.1.0.dist-info/entry_points.txt
epubcheck-5.1.0.dist-info/LICENSE
epubcheck-5.1.0.dist-info/METADATA
epubcheck-5.1.0.dist-info/WHEEL
epubcheck-5.1.0.dist-info/RECORD
