Metadata-Version: 2.1
Name: epubcheck
Version: 5.1.0
Summary: Python epubcheck wrapper
Home-page: https://github.com/titusz/epubcheck/
License: BSD
Keywords: EPUB,validation,epubcheck,ebooks,QA,IDPF
Author: Titusz Pan
Author-email: tp@py7.de
Requires-Python: >=3.8
Classifier: Development Status :: 4 - Beta
Classifier: Intended Audience :: Developers
Classifier: License :: OSI Approved :: BSD License
Classifier: License :: Other/Proprietary License
Classifier: Operating System :: Microsoft :: Windows
Classifier: Operating System :: POSIX
Classifier: Operating System :: Unix
Classifier: Programming Language :: Python
Classifier: Programming Language :: Python :: 3
Classifier: Programming Language :: Python :: 3.8
Classifier: Programming Language :: Python :: 3.9
Classifier: Programming Language :: Python :: 3.10
Classifier: Programming Language :: Python :: 3.11
Classifier: Programming Language :: Python :: 3.12
Classifier: Programming Language :: Python :: Implementation :: CPython
Classifier: Programming Language :: Python :: Implementation :: PyPy
Requires-Dist: tablib
Requires-Dist: xlrd
Requires-Dist: xlwt
Project-URL: Repository, https://github.com/titusz/epubcheck/
